metricflow/__init__.py
metricflow/aggregation_properties.py
metricflow/api/__init__.py
metricflow/api/metricflow_client.py
metricflow/cli/__init__.py
metricflow/cli/cli_context.py
metricflow/cli/constants.py
metricflow/cli/custom_click_types.py
metricflow/cli/main.py
metricflow/cli/sample_models/countries.yaml
metricflow/cli/sample_models/customers.yaml
metricflow/cli/sample_models/transactions.yaml
metricflow/cli/tutorial.py
metricflow/cli/utils.py
metricflow/column_assoc.py
metricflow/configuration/__init__.py
metricflow/configuration/config_builder.py
metricflow/configuration/config_handler.py
metricflow/configuration/constants.py
metricflow/configuration/env_var.py
metricflow/configuration/yaml_handler.py
metricflow/constraints/__init__.py
metricflow/constraints/time_constraint.py
metricflow/dag/__init__.py
metricflow/dag/dag_to_text.py
metricflow/dag/dag_visualization.py
metricflow/dag/id_generation.py
metricflow/dag/mf_dag.py
metricflow/dataclass_serialization.py
metricflow/dataflow/__init__.py
metricflow/dataflow/builder/__init__.py
metricflow/dataflow/builder/costing.py
metricflow/dataflow/builder/dataflow_plan_builder.py
metricflow/dataflow/builder/measure_additiveness.py
metricflow/dataflow/builder/node_data_set.py
metricflow/dataflow/builder/node_evaluator.py
metricflow/dataflow/builder/partitions.py
metricflow/dataflow/builder/source_node.py
metricflow/dataflow/dataflow_plan.py
metricflow/dataflow/dataflow_plan_to_text.py
metricflow/dataflow/sql_column.py
metricflow/dataflow/sql_table.py
metricflow/dataset/__init__.py
metricflow/dataset/convert_data_source.py
metricflow/dataset/data_source_adapter.py
metricflow/dataset/dataset.py
metricflow/engine/__init__.py
metricflow/engine/metricflow_engine.py
metricflow/engine/models.py
metricflow/engine/time_source.py
metricflow/engine/utils.py
metricflow/errors/__init__.py
metricflow/errors/errors.py
metricflow/execution/__init__.py
metricflow/execution/execution_plan.py
metricflow_lite-0.130.2.dist-info/entry_points.txt
metricflow_lite-0.130.2.dist-info/LICENSE
metricflow_lite-0.130.2.dist-info/WHEEL
metricflow_lite-0.130.2.dist-info/METADATA
metricflow_lite-0.130.2.dist-info/RECORD
