Metadata-Version: 2.1
Name: metricflow-lite
Version: 0.130.2
Summary: Lite version of MetricFlow. This version is missing dependencies for using connectors with data warehouses
Home-page: https://transform.co/metricflow
License: AGPL-3.0-or-later
Author: Transform
Author-email: hello@transformdata.io
Requires-Python: >=3.8,<3.10
Classifier: License :: OSI Approved :: GNU Affero General Public License v3 or later (AGPLv3+)
Classifier: Programming Language :: Python :: 3
Classifier: Programming Language :: Python :: 3.8
Classifier: Programming Language :: Python :: 3.9
Provides-Extra: dbt-bigquery
Provides-Extra: dbt-postgres
Provides-Extra: dbt-redshift
Provides-Extra: dbt-snowflake
Requires-Dist: GitPython (>=3.1.27,<4.0.0)
Requires-Dist: Jinja2 (>=2.11.3)
Requires-Dist: MarkupSafe (==2.0.1)
Requires-Dist: PyYAML (>=6.0,<7.0)
Requires-Dist: SQLAlchemy (>=1.4.27,<2.0.0)
Requires-Dist: click (>=7.1.2)
Requires-Dist: croniter (>=1.3.4,<2.0.0)
Requires-Dist: databricks-sql-connector (==2.0.3)
Requires-Dist: dbt-bigquery (>=1.3.0,<2.0.0); extra == "dbt-bigquery"
Requires-Dist: dbt-postgres (>=1.3.0,<2.0.0); extra == "dbt-postgres"
Requires-Dist: dbt-redshift (>=1.3.0,<2.0.0); extra == "dbt-redshift"
Requires-Dist: dbt-snowflake (>=1.3.0,<2.0.0); extra == "dbt-snowflake"
Requires-Dist: duckdb (==0.3.4)
Requires-Dist: duckdb-engine (>=0.1.8,<0.2.0)
Requires-Dist: fuzzywuzzy (>=0.18.0,<0.19.0)
Requires-Dist: graphviz (==0.18.2)
Requires-Dist: halo (>=0.0.31,<0.0.32)
Requires-Dist: jsonschema (==3.2.0)
Requires-Dist: more-itertools (==8.10.0)
Requires-Dist: moz-sql-parser (>=4.40.21126,<5.0.0)
Requires-Dist: numpy (>=1.22.2)
Requires-Dist: pandas (>=1.3.0,<2.0.0)
Requires-Dist: pycron (>=3.0.0,<4.0.0)
Requires-Dist: pydantic (>=1.9.0,<2.0.0)
Requires-Dist: python-dateutil (==2.8.2)
Requires-Dist: requests (>=2.27.1,<3.0.0)
Requires-Dist: ruamel.yaml (>=0.17.21,<0.18.0)
Requires-Dist: rudder-sdk-python (>=1.0.3,<2.0.0)
Requires-Dist: snowflake-sqlalchemy (==1.2.3)
Requires-Dist: sqlalchemy-bigquery (>=1.4.3,<2.0.0)
Requires-Dist: sqlalchemy-redshift (==0.8.1)
Requires-Dist: sqlalchemy2-stubs (>=0.0.2-alpha.21,<0.0.3)
Requires-Dist: tabulate (==0.8.9)
Requires-Dist: typing_extensions (>=4.0.0)
Requires-Dist: update-checker (>=0.18.0,<0.19.0)
Requires-Dist: yamllint (>=1.26.3,<2.0.0)
Project-URL: Repository, https://github.com/transform-data/metricflow-lite
